<DOMSymbolItem xmlns:xsi="http://www.w3.org/2001/XMLSchema-instance" xmlns="http://ns.adobe.com/xfl/2008/" name="main" itemID="5751cf38-00000018" lastModified="1465304323">
  <persistentData>
    <PD n="CreateJSToolkit_timelinedata" v="version&#xA;0.1&#xA;loop&#xA;true"/>
  </persistentData>
  <timeline>
    <DOMTimeline name="main">
      <layers>
        <DOMLayer name="Layer 1" color="#4F80FF" current="true" isSelected="true">
          <frames>
            <DOMFrame index="0" duration="120" keyMode="9728">
              <elements>
                <DOMSymbolInstance libraryItemName="pt-logo-unfolding" symbolType="graphic" centerPoint3DX="2.4" centerPoint3DY="-0.9" loop="play once">
                  <matrix>
                    <Matrix a="0.5" d="0.5" ty="-10"/>
                  </matrix>
                  <transformationPoint>
                    <Point y="20"/>
                  </transformationPoint>
                </DOMSymbolInstance>
              </elements>
            </DOMFrame>
          </frames>
        </DOMLayer>
      </layers>
    </DOMTimeline>
  </timeline>
</DOMSymbolItem>